albumplayer/__init__.py
albumplayer/albumplayer.py
keywind_albumplayer-1.0.1.dist-info/LICENSE
keywind_albumplayer-1.0.1.dist-info/METADATA
keywind_albumplayer-1.0.1.dist-info/WHEEL
keywind_albumplayer-1.0.1.dist-info/top_level.txt
keywind_albumplayer-1.0.1.dist-info/RECORD
