Metadata-Version: 2.1
Name: keywind-albumplayer
Version: 1.0.1
Summary: Installing this package will allow you to play music albums.
Home-page: https://github.com/keywind1207/keywind-albumplayer
Author: Keywind
Author-email: keywind127@gmail.com
License: UNKNOWN
Project-URL: Bug Tracker, https://github.com/keywind1207/keywind-albumplayer/issues
Platform: UNKNOWN
Classifier: Programming Language :: Python :: 3
Classifier: License :: OSI Approved :: MIT License
Classifier: Operating System :: OS Independent
Requires-Python: >=3.6
License-File: LICENSE
Requires-Dist: markdown
Requires-Dist: pynput
Requires-Dist: wave
Requires-Dist: pyaudio
